{
  "ShinyColors": [
    {
      "Name": "櫻木真乃",
      "Phonetic": "さくらぎまの",
      "English": "Sakuragi Mano",
      "Age": 16,
      "Height": 155,
      "Weight": 48,
      "Bust": 86,
      "Waist": 58,
      "Hip": 88,
      "BirthDay": "04/25",
      "Blood": "A",
      "BirthPlace": "東京",
      "Hobby": "お出かけ,公園で日向ぼっこ",
      "Talent": "鳥に好かれる",
      "Constellation": "牡牛座",
      "Handedness": "right",
      "Color": "FFBAD6"
    },
    {
      "Name": "八宮めぐる",
      "Phonetic": "はちみやめぐる",
      "English": "Hachimiya Meguru",
      "Age": 16,
      "Height": 157,
      "Weight": 46,
      "Bust": 90,
      "Waist": 59,
      "Hip": 89,
      "BirthDay": "07/22",
      "Blood": "O",
      "BirthPlace": "アメリカ　マサチューセッツ州",
      "Hobby": "人と話すこと,体を動かすこと",
      "Talent": "スポーツ全般",
      "Constellation": "蟹座",
      "Handedness": "right",
      "Color": "FFE012"
    },
    {
      "Name": "風野灯織",
      "Phonetic": "かざのひおり",
      "English": "Kazano Hiori",
      "Age": 15,
      "Height": 154,
      "Weight": 43,
      "Bust": 75,
      "Waist": 55,
      "Hip": 78,
      "BirthDay": "03/04",
      "Blood": "A",
      "BirthPlace": "東京",
      "Hobby": "音楽鑑賞,綺麗な景色を探すこと,占い",
      "Talent": "料理,スケジュール管理",
      "Constellation": "魚座",
      "Handedness": "right",
      "Color": "144384"
    },
    {
      "Name": "月岡恋鐘",
      "Phonetic": "つきおかこがね",
      "English": "Tsukioka Kogane",
      "Age": 19,
      "Height": 165,
      "Weight": 58,
      "Bust": 93,
      "Waist": 60,
      "Hip": 91,
      "BirthDay": "02/25",
      "Blood": "B",
      "BirthPlace": "長崎",
      "Hobby": "うちの手料理、なんでも絶品たい！",
      "Talent": "そっくりな似顔絵は描けるたい！",
      "Constellation": "魚座",
      "Handedness": "left",
      "Color": "F94CAD"
    },
    {
      "Name": "三峰結華",
      "Phonetic": "みつみねゆいか",
      "English": "Mitsumine Yuika",
      "Age": 19,
      "Height": 158,
      "Weight": 44,
      "Bust": 73,
      "Waist": 52,
      "Hip": 81,
      "BirthDay": "01/16",
      "Blood": "O",
      "BirthPlace": "福島",
      "Hobby": "アイドルライブ鑑賞,カメラ,ゲーム,アニメ,読書",
      "Talent": "勉強,推しに一早く認知されること",
      "Constellation": "山羊座",
      "Handedness": "right",
      "Color": "3B91C4"
    },
    {
      "Name": "白瀬咲耶",
      "Phonetic": "しらせさくや",
      "English": "Shirase Sakuya",
      "Age": 18,
      "Height": 175,
      "Weight": 60,
      "Bust": 91,
      "Waist": 58,
      "Hip": 87,
      "BirthDay": "06/27",
      "Blood": "A",
      "BirthPlace": "高知",
      "Hobby": "色々な所に出かける",
      "Talent": "自分を最大限カッコ良く見せる立ち振る舞い",
      "Constellation": "蟹座",
      "Handedness": "right",
      "Color": "006047"
    },
    {
      "Name": "田中摩美々",
      "Phonetic": "たなかまみみ",
      "English": "Tanaka Mamimi",
      "Age": 18,
      "Height": 161,
      "Weight": 49,
      "Bust": 81,
      "Waist": 56,
      "Hip": 83,
      "BirthDay": "05/24",
      "Blood": "B",
      "BirthPlace": "神奈川",
      "Hobby": "放浪,人をからかう",
      "Talent": "自分で髪を切る",
      "Constellation": "双子座",
      "Handedness": "right",
      "Color": "A846FB"
    },
    {
      "Name": "幽谷霧子",
      "Phonetic": "ゆうこくきりこ",
      "English": "Yukoku Kiriko",
      "Age": 17,
      "Height": 160,
      "Weight": 51,
      "Bust": 79,
      "Waist": 55,
      "Hip": 81,
      "BirthDay": "09/23",
      "Blood": "AB",
      "BirthPlace": "青森",
      "Hobby": "かわいいもの全般の収集,手芸,献血",
      "Talent": "包帯を綺麗に巻く,足音を立てない,りんごの皮むき",
      "Constellation": "天秤座",
      "Handedness": "left",
      "Color": "D9F2DD"
    },
    {
      "Name": "桑山千雪",
      "Phonetic": "くわやまちゆき",
      "English": "Kuwayama Chiyuki",
      "Age": 23,
      "Height": 163,
      "Weight": 47,
      "Bust": 89,
      "Waist": 58,
      "Hip": 92,
      "BirthDay": "04/18",
      "Blood": "A",
      "BirthPlace": "山口",
      "Hobby": "雑貨作り",
      "Talent": "裁縫,道案内",
      "Constellation": "牡牛座",
      "Handedness": "right",
      "Color": "FBFBFB"
    },
    {
      "Name": "大崎甜花",
      "Phonetic": "おおさきてんか",
      "English": "Osaki Tenka",
      "Age": 17,
      "Height": 159,
      "Weight": 44,
      "Bust": 81,
      "Waist": 58,
      "Hip": 83,
      "BirthDay": "12/25",
      "Blood": "A",
      "BirthPlace": "富山",
      "Hobby": "お昼寝,ネットサーフィン,アニメ,ゲーム",
      "Talent": "特に無い",
      "Constellation": "山羊座",
      "Handedness": "right",
      "Color": "E75BEC"
    },
    {
      "Name": "大崎甘奈",
      "Phonetic": "おおさきあまな",
      "English": "Osaki Amana",
      "Age": 17,
      "Height": 159,
      "Weight": 43,
      "Bust": 80,
      "Waist": 56,
      "Hip": 80,
      "BirthDay": "12/25",
      "Blood": "A",
      "BirthPlace": "富山",
      "Hobby": "ショッピング,ネイル,自撮り",
      "Talent": "早起き,倹約",
      "Constellation": "山羊座",
      "Handedness": "right",
      "Color": "F54275"
    },
    {
      "Name": "小宮果穂",
      "Phonetic": "こみやかほ",
      "English": "Komiya Kaho",
      "Age": 12,
      "Height": 163,
      "Weight": 45,
      "Bust": 80,
      "Waist": 57,
      "Hip": 83,
      "BirthDay": "07/29",
      "Blood": "A",
      "BirthPlace": "東京",
      "Hobby": "日曜日朝の子供向け番組を見る事,グッズ集め",
      "Talent": "好きな番組の決め台詞を数多く覚えている",
      "Constellation": "獅子座",
      "Handedness": "right",
      "Color": "E75029"
    },
    {
      "Name": "西城樹里",
      "Phonetic": "さいじょうじゅり",
      "English": "Saijo Juri",
      "Age": 17,
      "Height": 160,
      "Weight": 48,
      "Bust": 75,
      "Waist": 58,
      "Hip": 78,
      "BirthDay": "11/26",
      "Blood": "O",
      "BirthPlace": "神奈川",
      "Hobby": "洋楽,ゲーム",
      "Talent": "スポーツ全般,（中２までは）バスケ",
      "Constellation": "射手座",
      "Handedness": "right",
      "Color": "FFCB13"
    },
    {
      "Name": "有栖川夏葉",
      "Phonetic": "ありすがわなつは",
      "English": "Arisugawa Natsuha",
      "Age": 20,
      "Height": 168,
      "Weight": 49,
      "Bust": 85,
      "Waist": 58,
      "Hip": 84,
      "BirthDay": "08/16",
      "Blood": "B",
      "BirthPlace": "愛知",
      "Hobby": "トレーニング,ストレッチ",
      "Talent": "トータルコーディネート",
      "Constellation": "獅子座",
      "Handedness": "right",
      "Color": "90E667"
    },
    {
      "Name": "杜野凛世",
      "Phonetic": "もりのりんぜ",
      "English": "Morino Rinze",
      "Age": 16,
      "Height": 155,
      "Weight": 44,
      "Bust": 70,
      "Waist": 54,
      "Hip": 78,
      "BirthDay": "10/19",
      "Blood": "B",
      "BirthPlace": "鳥取",
      "Hobby": "少女漫画,芸道全般",
      "Talent": "折り紙,百人一首",
      "Constellation": "天秤座",
      "Handedness": "left",
      "Color": "84C0EA"
    },
    {
      "Name": "園田智代子",
      "Phonetic": "そのだちよこ",
      "English": "Sonoda Chiyoko",
      "Age": 17,
      "Height": 149,
      "Weight": 46,
      "Bust": 85,
      "Waist": 56,
      "Hip": 82,
      "BirthDay": "02/24",
      "Blood": "A",
      "BirthPlace": "千葉",
      "Hobby": "スイーツ店巡り",
      "Talent": "たくさん食べられること",
      "Constellation": "魚座",
      "Handedness": "right",
      "Color": "F93B90"
    },
    {
      "Name": "黛冬優子",
      "Phonetic": "まゆずみふゆこ",
      "English": "Mayuzumni Fuyuko",
      "Age": 19,
      "Height": 163,
      "Weight": 55,
      "Bust": 78,
      "Waist": 59,
      "Hip": 81,
      "BirthDay": "12/04",
      "Blood": "A",
      "BirthPlace": "茨城",
      "Hobby": "お友達とおしゃべり♪",
      "Talent": "みんなと仲良くなること♪",
      "Constellation": "射手座",
      "Handedness": "right",
      "Color": "5CE626"
    },
    {
      "Name": "芹沢あさひ",
      "Phonetic": "せりざわあさひ",
      "English": "Serizawa Asahi",
      "Age": 14,
      "Height": 153,
      "Weight": 47,
      "Bust": 78,
      "Waist": 58,
      "Hip": 77,
      "BirthDay": "01/04",
      "Blood": "AB",
      "BirthPlace": " 東京",
      "Hobby": "人間観察,人に話しかけること",
      "Talent": "記憶力がいい",
      "Constellation": "山羊座",
      "Handedness": "both",
      "Color": "F30100"
    },
    {
      "Name": "和泉愛依",
      "Phonetic": "いずみめい",
      "English": "Izumi Mei",
      "Age": 18,
      "Height": 162,
      "Weight": 51,
      "Bust": 90,
      "Waist": 58,
      "Hip": 88,
      "BirthDay": "08/02",
      "Blood": "O",
      "BirthPlace": "埼玉",
      "Hobby": "友達と遊ぶ,最近の曲を聞く",
      "Talent": "何時間でも電話できること",
      "Constellation": "獅子座",
      "Handedness": "right",
      "Color": "FF00FF"
    }
  ]
}